pyDictStore/__decorators__.py
pyDictStore/__events__.py
pyDictStore/__init__.py
pyDictStore-1.0.4.dist-info/LICENSE
pyDictStore-1.0.4.dist-info/METADATA
pyDictStore-1.0.4.dist-info/WHEEL
pyDictStore-1.0.4.dist-info/top_level.txt
pyDictStore-1.0.4.dist-info/RECORD
