Metadata-Version: 2.1
Name: pyDictStore
Version: 1.0.4
Summary: pyDictStore adds automated dictionary storage to properties eliminating the need for code bodies, property getters and setters. It also provides a property change event.
Home-page: https://OpenWayside.org
Author: Peter Varney, OpenWayside
Author-email: pyDictStore@OpenWayside.org
License: UNKNOWN
Project-URL: Documentation, https://openwayside.org/rtm/pyDictStore/
Project-URL: Source, https://github.com/OpenWayside/pyDictStore
Project-URL: Issues, https://github.com/OpenWayside/pyDictStore/issues
Platform: UNKNOWN
Classifier: Programming Language :: Python :: 3
Classifier: License :: OSI Approved :: MIT License
Classifier: Operating System :: OS Independent
Requires-Python: >=3.10
License-File: LICENSE
